thesys_genui_sdk/__init__.py
thesys_genui_sdk/c1_response.py
thesys_genui_sdk/context.py
thesys_genui_sdk/fast_api.py
thesys_genui_sdk/xml_utils.py
thesys_genui_sdk-0.1.1.dist-info/METADATA
thesys_genui_sdk-0.1.1.dist-info/WHEEL
thesys_genui_sdk-0.1.1.dist-info/RECORD
