Metadata-Version: 2.1
Name: thesys_genui_sdk
Version: 0.1.1
Summary: Thesys GenUI utilities
Author: Thesys Inc.
Author-email: engineering@thesys.dev
Requires-Python: >=3.10,<4.0
Classifier: Programming Language :: Python :: 3
Classifier: Programming Language :: Python :: 3.10
Classifier: Programming Language :: Python :: 3.11
Classifier: Programming Language :: Python :: 3.12
